pycpil/__init__.py
pycpil/cpil.py
pycpil-1.0.2.dist-info/METADATA
pycpil-1.0.2.dist-info/WHEEL
pycpil-1.0.2.dist-info/top_level.txt
pycpil-1.0.2.dist-info/RECORD
